app/__init__.py
app/cli.py
app/config_manager.py
app/hsv_thresholder.py
app/image_processor.py
app/plate.py
app/visualizer.py
app/well_analyzer.py
app/well_detector.py
lemna-0.1.1.dist-info/METADATA
lemna-0.1.1.dist-info/WHEEL
lemna-0.1.1.dist-info/entry_points.txt
lemna-0.1.1.dist-info/top_level.txt
lemna-0.1.1.dist-info/RECORD
