Metadata-Version: 2.4
Name: lemna
Version: 0.1.1
Summary: Toolset for analysis of plant growth in wells.
Author-email: Jon Snow <jms8@comcast.net>
License: MIT
Requires-Python: >=3.8
Requires-Dist: Click
Requires-Dist: opencv-python
Requires-Dist: numpy
Requires-Dist: toml
Requires-Dist: scikit-learn
